{
  "version": "3.21.1",
  "flags": {},
  "shapes": [
    {
      "label": "dot",
      "line_color": null,
      "fill_color": null,
      "points": [
        [
          2424.0,
          1968.0
        ],
        [
          2413.5714285714284,
          2007.0
        ],
        [
          2385.0,
          2035.5714285714287
        ],
        [
          2346.0,
          2046.0
        ],
        [
          2307.0,
          2035.5714285714287
        ],
        [
          2278.4285714285716,
          2007.0
        ],
        [
          2268.0,
          1968.0
        ],
        [
          2278.4285714285716,
          1929.0
        ],
        [
          2307.0,
          1900.4285714285713
        ],
        [
          2346.0,
          1890.0
        ],
        [
          2385.0,
          1900.4285714285713
        ],
        [
          2413.5714285714284,
          1929.0
        ]
      ],
      "shape_type": "polygon",
      "flags": {}
    },
    {
      "label": "dot",
      "line_color": null,
      "fill_color": null,
      "points": [
        [
          1567.0,
          1328.0
        ],
        [
          1557.5,
          1356.0
        ],
        [
          1531.5,
          1376.5
        ],
        [
          1496.0,
          1384.0
        ],
        [
          1460.5,
          1376.5
        ],
        [
          1434.5,
          1356.0
        ],
        [
          1425.0,
          1328.0
        ],
        [
          1434.5,
          1300.0
        ],
        [
          1460.5,
          1279.5
        ],
        [
          1496.0,
          1272.0
        ],
        [
          1531.5,
          1279.5
        ],
        [
          1557.5,
          1300.0
        ]
      ],
      "shape_type": "polygon",
      "flags": {}
    },
    {
      "label": "dot",
      "line_color": null,
      "fill_color": null,
      "points": [
        [
          2576.0,
          709.0
        ],
        [
          2569.1428571428573,
          735.5
        ],
        [
          2550.5,
          754.9285714285714
        ],
        [
          2525.0,
          762.0
        ],
        [
          2499.5,
          754.9285714285714
        ],
        [
          2480.8571428571427,
          735.5
        ],
        [
          2474.0,
          709.0
        ],
        [
          2480.8571428571427,
          682.5
        ],
        [
          2499.5,
          663.0714285714286
        ],
        [
          2525.0,
          656.0
        ],
        [
          2550.5,
          663.0714285714286
        ],
        [
          2569.1428571428573,
          682.5
        ]
      ],
      "shape_type": "polygon",
      "flags": {}
    },
    {
      "label": "dot",
      "line_color": null,
      "fill_color": null,
      "points": [
        [
          969.0,
          1017.0
        ],
        [
          958.5714285714286,
          1056.0
        ],
        [
          930.0,
          1084.5714285714287
        ],
        [
          891.0,
          1095.0
        ],
        [
          852.0,
          1084.5714285714287
        ],
        [
          823.4285714285714,
          1056.0
        ],
        [
          813.0,
          1017.0
        ],
        [
          823.4285714285714,
          978.0
        ],
        [
          852.0,
          949.4285714285714
        ],
        [
          891.0,
          939.0
        ],
        [
          930.0,
          949.4285714285714
        ],
        [
          958.5714285714286,
          978.0
        ]
      ],
      "shape_type": "polygon",
      "flags": {}
    }
  ],
  "lineColor": [
    0,
    255,
    0,
    128
  ],
  "fillColor": [
    255,
    0,
    0,
    128
  ],
  "imagePath": "s2_008_aug_6_piece_1.jpg",
  "imageData": "",
  "imageHeight": 2012,
  "imageWidth": 3072
}