{
  "version": "3.21.1",
  "flags": {},
  "shapes": [
    {
      "label": "dot",
      "line_color": null,
      "fill_color": null,
      "points": [
        [
          2312.0,
          1349.0
        ],
        [
          2301.5714285714284,
          1389.5
        ],
        [
          2273.0,
          1419.142857142857
        ],
        [
          2234.0,
          1430.0
        ],
        [
          2195.0,
          1419.142857142857
        ],
        [
          2166.4285714285716,
          1389.5
        ],
        [
          2156.0,
          1349.0
        ],
        [
          2166.4285714285716,
          1308.5
        ],
        [
          2195.0,
          1278.857142857143
        ],
        [
          2234.0,
          1268.0
        ],
        [
          2273.0,
          1278.857142857143
        ],
        [
          2301.5714285714284,
          1308.5
        ]
      ],
      "shape_type": "polygon",
      "flags": {}
    }
  ],
  "lineColor": [
    0,
    255,
    0,
    128
  ],
  "fillColor": [
    255,
    0,
    0,
    128
  ],
  "imagePath": "s3_006_aug_6_piece_7.jpg",
  "imageData": "",
  "imageHeight": 2012,
  "imageWidth": 3072
}