{
  "version": "3.21.1",
  "flags": {},
  "shapes": [
    {
      "label": "dot",
      "line_color": null,
      "fill_color": null,
      "points": [
        [
          1308.0,
          1526.0
        ],
        [
          1298.857142857143,
          1557.5
        ],
        [
          1274.0,
          1580.5714285714287
        ],
        [
          1240.0,
          1589.0
        ],
        [
          1206.0,
          1580.5714285714287
        ],
        [
          1181.142857142857,
          1557.5
        ],
        [
          1172.0,
          1526.0
        ],
        [
          1181.142857142857,
          1494.5
        ],
        [
          1206.0,
          1471.4285714285713
        ],
        [
          1240.0,
          1463.0
        ],
        [
          1274.0,
          1471.4285714285713
        ],
        [
          1298.857142857143,
          1494.5
        ]
      ],
      "shape_type": "polygon",
      "flags": {}
    },
    {
      "label": "dot",
      "line_color": null,
      "fill_color": null,
      "points": [
        [
          1377.0,
          1830.0
        ],
        [
          1368.857142857143,
          1861.5
        ],
        [
          1346.5,
          1884.5714285714287
        ],
        [
          1316.0,
          1893.0
        ],
        [
          1285.5,
          1884.5714285714287
        ],
        [
          1263.142857142857,
          1861.5
        ],
        [
          1255.0,
          1830.0
        ],
        [
          1263.142857142857,
          1798.5
        ],
        [
          1285.5,
          1775.4285714285713
        ],
        [
          1316.0,
          1767.0
        ],
        [
          1346.5,
          1775.4285714285713
        ],
        [
          1368.857142857143,
          1798.5
        ]
      ],
      "shape_type": "polygon",
      "flags": {}
    }
  ],
  "lineColor": [
    0,
    255,
    0,
    128
  ],
  "fillColor": [
    255,
    0,
    0,
    128
  ],
  "imagePath": "s4_006_aug_7_piece_8.jpg",
  "imageData": "",
  "imageHeight": 2012,
  "imageWidth": 3072
}